rocketchat_auth
